{
    "nepali_date": {
        "formated": "рей рдЕрд╕рд╛рд░ реирежренрем, рдордВрдЧрд▓рд╡рд╛рд░",
        "day": "рей",
        "month": "рдЕрд╕рд╛рд░",
        "year": "реирежренрем",
        "day_name": "рдордВрдЧрд▓рд╡рд╛рд░",
        "date": "2076-03-03"
    },
    "english_date": {
        "formated": "June 18, 2019",
        "day": "18",
        "month": "June",
        "year": "2019",
        "day_name": "Tuesday",
        "date": "2019-06-18"
    },
    "nepali_sambat": {
        "formated": "1139 рддрдЫрд▓рд╛рдЧрд╛ рдкрд╛рд░реБ-16",
        "year": "1139",
        "month": "рддрдЫрд▓рд╛рдЧрд╛",
        "tithi": "рдкрд╛рд░реБ-16"
    },
    "event": "--",
    "is_holiday": false,
    "panchang": {
        "surya": "5:09тШАя╕П, 19:02ЁЯМд",
        "chandra": "20:03тШ╜, 5:56тШ╛",
        "tithi": "рдкреНрд░рддрд┐рдкрджрд╛ upto 14:50:51, рдЙрдкрд░рд╛рдиреНрдд: рджреНрд╡рд┐рддреАрдпрд╛",
        "pakshya": "рдЖрд╖рд╛рдв рдХреГрд╖реНрдг рдкрдХреНрд╖ ЁЯМЦ",
        "nakshatra": "рдореВрд▓ upto 12:9:53, рдЙрдкрд░рд╛рдиреНрдд: рдкреВрд░реНрд╡рд╛рд╖рд╛рдврд╛",
        "yoga": "рд╢реБрдХреНрд▓ upto 19:20:33, рдЙрдкрд░рд╛рдиреНрдд: рдмреНрд░рд╣реНрдо",
        "karan": "рдХреМрд▓рд╡ upto 14:50:51",
        "chandra_rashi": "рдзрдиреБ тЩР",
        "dinman": "34 рдШрдбреА 42 рдкрд▓рд╛ - 13hr 53min",
        "ritu": "рдЧреНрд░реАрд╖реНрдо-Summer",
        "ayan": "рдЙрддреНрддрд░рд╛рдпрдг"
    }
}