{
    "nepali_date": {
        "formated": "рез рдордВрд╕рд┐рд░ реирежреорез, рд╢рдирд┐рд╡рд╛рд░",
        "day": "рез",
        "month": "рдордВрд╕рд┐рд░",
        "year": "реирежреорез",
        "day_name": "рд╢рдирд┐рд╡рд╛рд░",
        "date": "2081-08-01"
    },
    "english_date": {
        "formated": "November 16, 2024",
        "day": "16",
        "month": "November",
        "year": "2024",
        "day_name": "Saturday",
        "date": "2024-11-16"
    },
    "nepali_sambat": {
        "formated": "1145 рдХрдЫрд▓рд╛рдЧрд╛ рдкрд╛рд░реБ - 16",
        "year": "1145",
        "month": "рдХрдЫрд▓рд╛рдЧрд╛",
        "tithi": "рдкрд╛рд░реБ - 16"
    },
    "event": "рд╡реГрд╢реНрдЪрд┐рдХ рд╕рдВрдХреНрд░рд╛рдиреНрддрд┐",
    "is_holiday": true,
    "panchang": {
        "surya": "6:26тШАя╕П, 17:12ЁЯМд",
        "chandra": "5:26 PMтШ╜, 6:56 AMтШ╛",
        "tithi": "рдкреНрд░рддрд┐рдкрджрд╛ upto 24:9:30, рдЙрдкрд░рд╛рдиреНрдд: рджреНрд╡рд┐рддреАрдпрд╛",
        "pakshya": "рдордВрд╕рд┐рд░ рдХреГрд╖реНрдг рдкрдХреНрд╖ ЁЯМЦ",
        "nakshatra": "рдХреГрддреНрддрд┐рдХрд╛ upto 19:47:35, рдЙрдкрд░рд╛рдиреНрдд: рд░реЛрд╣рд┐рдгреА",
        "yoga": "рдкрд░рд┐рдШ upto 24:6:8, рдЙрдкрд░рд╛рдиреНрдд: рд╢рд┐рд╡",
        "karan": "рдмрд╛рд▓рд╡ upto 13:41:23, рдЙрдкрд░рд╛рдиреНрдд: рдХреМрд▓рд╡ upto 24:9:30",
        "chandra_rashi": "рд╡реГрд╖ тЩЙ",
        "dinman": "26 рдШрдбреА 55 рдкрд▓рд╛ - 10hr 46min",
        "ritu": "рд╣реЗрдордиреНрдд - Pre-winter",
        "ayan": "рджрдХреНрд╖рд┐рдгрд╛рдпрди"
    }
}