{
    "nepali_date": {
        "formated": "реирео рдордВрд╕рд┐рд░ реирежреореж, рдмрд┐рд╣рд┐рд╡рд╛рд░",
        "day": "реирео",
        "month": "рдордВрд╕рд┐рд░",
        "year": "реирежреореж",
        "day_name": "рдмрд┐рд╣рд┐рд╡рд╛рд░",
        "date": "2080-08-28"
    },
    "english_date": {
        "formated": "December 14, 2023",
        "day": "14",
        "month": "December",
        "year": "2023",
        "day_name": "Thursday",
        "date": "2023-12-14"
    },
    "nepali_sambat": {
        "formated": "1144 рдерд┐рдВрд▓рд╛рдереНрд╡ рджреНрд╡рд┐рддреАрдпрд╛-2",
        "year": "1144",
        "month": "рдерд┐рдВрд▓рд╛рдереНрд╡",
        "tithi": "рджреНрд╡рд┐рддреАрдпрд╛-2"
    },
    "event": "--",
    "is_holiday": false,
    "panchang": {
        "surya": "6:47тШАя╕П, 17:11ЁЯМд",
        "chandra": "8:04тШ╜, 18:16тШ╛",
        "tithi": "рджреНрд╡рд┐рддреАрдпрд╛ upto 25:11:20, рдЙрдкрд░рд╛рдиреНрдд: рддреГрддреАрдпрд╛",
        "pakshya": "рдордВрд╕рд┐рд░ рд╢реБрдХреНрд▓ рдкрдХреНрд╖ ЁЯМТ",
        "nakshatra": "рдореВрд▓ upto 10:2:2, рдЙрдкрд░рд╛рдиреНрдд: рдкреВрд░реНрд╡рд╛рд╖рд╛рдврд╛",
        "yoga": "рдЧрдгреНрдб upto 13:38:50, рдЙрдкрд░рд╛рдиреНрдд: рд╡реГрджреНрдзрд┐",
        "karan": "рдмрд╛рд▓рд╡ upto 14:19:10, рдЙрдкрд░рд╛рдиреНрдд: рдХреМрд▓рд╡ upto 25:11:20",
        "chandra_rashi": "рдзрдиреБ тЩР",
        "dinman": "26 рдШрдбреА 0 рдкрд▓рд╛ - 10hr 24min",
        "ritu": "рд╣реЗрдордиреНрдд-Pre-winter",
        "ayan": "рджрдХреНрд╖рд┐рдгрд╛рдпрди"
    }
}