{
    "nepali_date": {
        "formated": "рен рдЬреЗрда реирежренрен, рдмреБрдзрд╡рд╛рд░",
        "day": "рен",
        "month": "рдЬреЗрда",
        "year": "реирежренрен",
        "day_name": "рдмреБрдзрд╡рд╛рд░",
        "date": "2077-02-07"
    },
    "english_date": {
        "formated": "May 20, 2020",
        "day": "20",
        "month": "May",
        "year": "2020",
        "day_name": "Wednesday",
        "date": "2020-05-20"
    },
    "nepali_sambat": {
        "formated": "1140 рд╡рдЫрд▓рд╛рдЧрд╛ рддреНрд░рдпреЛрджрд╢реА-28",
        "year": "1140",
        "month": "рд╡рдЫрд▓рд╛рдЧрд╛",
        "tithi": "рддреНрд░рдпреЛрджрд╢реА-28"
    },
    "event": "рдЪрд▓рдЪрд┐рддреНрд░ рдкрддреНрд░рдХрд╛рд░рд┐рддрд╛ рджрд┐рд╡рд╕",
    "is_holiday": false,
    "panchang": {
        "surya": "5:13тШАя╕П, 18:49ЁЯМд",
        "chandra": "3:48тШ╜, 17:46тШ╛",
        "tithi": "рддреНрд░рдпреЛрджрд╢реА upto 19:57:22, рдЙрдкрд░рд╛рдиреНрдд: рдЪрддреБрд░реНрджрд╢реА",
        "pakshya": "рдЬреЗрд╖реНрда рдХреГрд╖реНрдг рдкрдХреНрд╖ ЁЯМШ",
        "nakshatra": "рдЕрд╢реНрд╡рд┐рдиреА upto 22:52:41, рдЙрдкрд░рд╛рдиреНрдд: рднрд░рдгреА",
        "yoga": "рдЖрдпреБрд╖реНрдорд╛рди upto 5:36:2, рдЙрдкрд░рд╛рдиреНрдд: рд╕реМрднрд╛рдЧреНрдп",
        "karan": "рдЧрд░ upto 6:55:8, рдЙрдкрд░рд╛рдиреНрдд: рд╡рдгрд┐рдЬ upto 19:57:22",
        "chandra_rashi": "рдореЗрд╖ тЩИ",
        "dinman": "34 рдШрдбреА 0 рдкрд▓рд╛ - 13hr 36min",
        "ritu": "рдЧреНрд░реАрд╖реНрдо-Summer",
        "ayan": "рдЙрддреНрддрд░рд╛рдпрдг"
    }
}