{
    "nepali_date": {
        "formated": "резрен рдордВрд╕рд┐рд░ реирежренрек, рдЖрдЗрддрд╡рд╛рд░",
        "day": "резрен",
        "month": "рдордВрд╕рд┐рд░",
        "year": "реирежренрек",
        "day_name": "рдЖрдЗрддрд╡рд╛рд░",
        "date": "2074-08-17"
    },
    "english_date": {
        "formated": "December 03, 2017",
        "day": "3",
        "month": "December",
        "year": "2017",
        "day_name": "Sunday",
        "date": "2017-12-03"
    },
    "nepali_sambat": {
        "formated": "1138 рдерд┐рдВрд▓рд╛рдереНрд╡ рдкреБрдиреНрд╣рд┐-15",
        "year": "1138",
        "month": "рдерд┐рдВрд▓рд╛рдереНрд╡",
        "tithi": "рдкреБрдиреНрд╣рд┐-15"
    },
    "event": "--",
    "is_holiday": false,
    "panchang": {
        "surya": "6:38тШАя╕П, 17:09ЁЯМд",
        "chandra": "17:09тШ╜, 5:52тШ╛",
        "tithi": "рдкреВрд░реНрдгрд┐рдорд╛ upto 21:31:49, рдЙрдкрд░рд╛рдиреНрдд: рдкреНрд░рддрд┐рдкрджрд╛",
        "pakshya": "рдордВрд╕рд┐рд░ рд╢реБрдХреНрд▓ рдкрдХреНрд╖ ЁЯМХ",
        "nakshatra": "рдХреГрддреНрддрд┐рдХрд╛ upto 9:36:37, рдЙрдкрд░рд╛рдиреНрдд: рд░реЛрд╣рд┐рдгреА",
        "yoga": "рд╢рд┐рд╡ upto 9:1:59, рдЙрдкрд░рд╛рдиреНрдд: рд╕рд┐рджреНрдз (рд╕рдорд╛рдкреНрддреА)",
        "karan": "рд╡рд┐рд╖реНрдЯрд┐ upto 11:23:45, рдЙрдкрд░рд╛рдиреНрдд: рдмрд╡ upto 21:31:49",
        "chandra_rashi": "рд╡реГрд╖ тЩЙ",
        "dinman": "26 рдШрдбреА 17 рдкрд▓рд╛ - 10hr 31min",
        "ritu": "рд╣реЗрдордиреНрдд-Pre-winter",
        "ayan": "рджрдХреНрд╖рд┐рдгрд╛рдпрди"
    }
}