{
    "nepali_date": {
        "formated": "рел рдЕрд╕реЛрдЬ реирежренрез, рдЖрдЗрддрд╡рд╛рд░",
        "day": "рел",
        "month": "рдЕрд╕реЛрдЬ",
        "year": "реирежренрез",
        "day_name": "рдЖрдЗрддрд╡рд╛рд░",
        "date": "2071-06-05"
    },
    "english_date": {
        "formated": "September 21, 2014",
        "day": "21",
        "month": "September",
        "year": "2014",
        "day_name": "Sunday",
        "date": "2014-09-21"
    },
    "nepali_sambat": {
        "formated": "1134 рдЮрд▓рд╛рдЧрд╛ рддреНрд░рдпреЛрджрд╢реА-28",
        "year": "1134",
        "month": "рдЮрд▓рд╛рдЧрд╛",
        "tithi": "рддреНрд░рдпреЛрджрд╢реА-28"
    },
    "event": "--",
    "is_holiday": false,
    "panchang": {
        "surya": "5:52тШАя╕П, 18:03ЁЯМд",
        "chandra": "3:09тШ╜, 16:11тШ╛",
        "tithi": "рддреНрд░рдпреЛрджрд╢реА upto 31:46:8 (Full Night)",
        "pakshya": "рдЕрд╕реЛрдЬ рдХреГрд╖реНрдг рдкрдХреНрд╖ ЁЯМШ",
        "nakshatra": "рдЕрд╢реНрд▓реЗрд╖рд╛ upto 9:39:18, рдЙрдкрд░рд╛рдиреНрдд: рдордШрд╛",
        "yoga": "рд╕рд┐рджреНрдз upto 20:47:47, рдЙрдкрд░рд╛рдиреНрдд: рд╕рд╛рдШреНрдп",
        "karan": "рдЧрд░ upto 18:32:53, рдЙрдкрд░рд╛рдиреНрдд: рд╡рдгрд┐рдЬ upto 31:46:8",
        "chandra_rashi": "рдХрд░реНрдХрдЯ тЩЛ upto 9:39:18, рдЙрдкрд░рд╛рдиреНрдд: рд╕рд┐рдВрд╣ тЩМ",
        "dinman": "30 рдШрдбреА 27 рдкрд▓рд╛ - 12hr 11min",
        "ritu": "рд╢рд░рджреН-Autumn",
        "ayan": "рджрдХреНрд╖рд┐рдгрд╛рдпрди"
    }
}