{
    "nepali_date": {
        "formated": "рей рдЕрд╕рд╛рд░ реирежренрео, рдмрд┐рд╣рд┐рд╡рд╛рд░",
        "day": "рей",
        "month": "рдЕрд╕рд╛рд░",
        "year": "реирежренрео",
        "day_name": "рдмрд┐рд╣рд┐рд╡рд╛рд░",
        "date": "2078-03-03"
    },
    "english_date": {
        "formated": "June 17, 2021",
        "day": "17",
        "month": "June",
        "year": "2021",
        "day_name": "Thursday",
        "date": "2021-06-17"
    },
    "nepali_sambat": {
        "formated": "1141 рддрдЫрд▓рд╛рдереНрд╡ рд╕рдкреНрддрдореА-7",
        "year": "1141",
        "month": "рддрдЫрд▓рд╛рдереНрд╡",
        "tithi": "рд╕рдкреНрддрдореА-7"
    },
    "event": "рд╡рд┐рд╢реНрд╡ рдорд░реБрднреВрдореАрдХрд░рдг рд░ рдЦрдбреЗрд░реА рд╡рд┐рд░реБрджреНрдз рд╕рдВрдШрд░реНрд╖ рджрд┐рд╡рд╕",
    "is_holiday": false,
    "panchang": {
        "surya": "5:08тШАя╕П, 19:02ЁЯМд",
        "chandra": "11:16тШ╜, N/AтШ╛",
        "tithi": "рд╕рдкреНрддрдореА upto 22:12:22, рдЙрдкрд░рд╛рдиреНрдд: рдЕрд╖реНрдЯрдореА",
        "pakshya": "рдЬреЗрд╖реНрда рд╢реБрдХреНрд▓ рдкрдХреНрд╖ ЁЯМУ",
        "nakshatra": "рдкреВрд░реНрд╡рдлрд╛рд▓реНрдЧреБрдиреА upto 22:26:11, рдЙрдкрд░рд╛рдиреНрдд: рдЙрддреНрддрд░рдлрд╛рд▓реНрдЧреБрдиреА",
        "yoga": "рд╡рдЬреНрд░ upto 7:4:52, рдЙрдкрд░рд╛рдиреНрдд: рд╕рд┐рджреНрдзрд┐ (рд╕рдорд╛рдкреНрддреА)",
        "karan": "рдЧрд░ upto 10:40:38, рдЙрдкрд░рд╛рдиреНрдд: рд╡рдгрд┐рдЬ upto 22:12:22",
        "chandra_rashi": "рд╕рд┐рдВрд╣ тЩМ upto 28:23:11, рдЙрдкрд░рд╛рдиреНрдд: рдХрдиреНрдпрд╛ тЩН",
        "dinman": "34 рдШрдбреА 45 рдкрд▓рд╛ - 13hr 54min",
        "ritu": "рдЧреНрд░реАрд╖реНрдо-Summer",
        "ayan": "рдЙрддреНрддрд░рд╛рдпрдг"
    }
}