{
    "nepali_date": {
        "formated": "рей рдкреБрд╖ реирежренреж, рдмреБрдзрд╡рд╛рд░",
        "day": "рей",
        "month": "рдкреБрд╖",
        "year": "реирежренреж",
        "day_name": "рдмреБрдзрд╡рд╛рд░",
        "date": "2070-09-03"
    },
    "english_date": {
        "formated": "December 18, 2013",
        "day": "18",
        "month": "December",
        "year": "2013",
        "day_name": "Wednesday",
        "date": "2013-12-18"
    },
    "nepali_sambat": {
        "formated": "1134 рдерд┐рдВрд▓рд╛рдЧрд╛ рдкрд╛рд░реБ-16",
        "year": "1134",
        "month": "рдерд┐рдВрд▓рд╛рдЧрд╛",
        "tithi": "рдкрд╛рд░реБ-16"
    },
    "event": "--",
    "is_holiday": false,
    "panchang": {
        "surya": "6:49тШАя╕П, 17:13ЁЯМд",
        "chandra": "18:17тШ╜, 7:17тШ╛",
        "tithi": "рдкреНрд░рддрд┐рдкрджрд╛ upto 17:35:10, рдЙрдкрд░рд╛рдиреНрдд: рджреНрд╡рд┐рддреАрдпрд╛",
        "pakshya": "рдкреМрд╖ рдХреГрд╖реНрдг рдкрдХреНрд╖ ЁЯМЦ",
        "nakshatra": "рдЖрд░реНрджреНрд░рд╛ upto 28:19:47, рдЙрдкрд░рд╛рдиреНрдд: рдкреБрдирд░реНрд╡рд╢реБ",
        "yoga": "рд╢реБрдХреНрд▓ upto 22:32:27, рдЙрдкрд░рд╛рдиреНрдд: рдмреНрд░рд╣реНрдо",
        "karan": "рдХреМрд▓рд╡ upto 17:35:10",
        "chandra_rashi": "рдорд┐рдереБрди тЩК",
        "dinman": "26 рдШрдбреА 0 рдкрд▓рд╛ - 10hr 24min",
        "ritu": "рд╣реЗрдордиреНрдд-Pre-winter",
        "ayan": "рджрдХреНрд╖рд┐рдгрд╛рдпрди"
    }
}