{
    "nepali_date": {
        "formated": "реирем рднрджреМ реирежренреп, рдЖрдЗрддрд╡рд╛рд░",
        "day": "реирем",
        "month": "рднрджреМ",
        "year": "реирежренреп",
        "day_name": "рдЖрдЗрддрд╡рд╛рд░",
        "date": "2079-05-26"
    },
    "english_date": {
        "formated": "September 11, 2022",
        "day": "11",
        "month": "September",
        "year": "2022",
        "day_name": "Sunday",
        "date": "2022-09-11"
    },
    "nepali_sambat": {
        "formated": "1142 рдЮрд▓рд╛рдЧрд╛ рдкрд╛рд░реБ-16",
        "year": "1142",
        "month": "рдЮрд▓рд╛рдЧрд╛",
        "tithi": "рдкрд╛рд░реБ-16"
    },
    "event": "рд╕реЛрд╣реНрд░рд╢реНрд░рд╛рджреНрдз рдкреНрд░рд╛рд░рдореНрдн (рдкреНрд░рддрд┐рдкрджрд╛ рд╢реНрд░рд╛рджреНрдз)",
    "is_holiday": false,
    "panchang": {
        "surya": "5:48тШАя╕П, 18:14ЁЯМд",
        "chandra": "19:07тШ╜, 6:30тШ╛",
        "tithi": "рдкреНрд░рддрд┐рдкрджрд╛ upto 13:36:6, рдЙрдкрд░рд╛рдиреНрдд: рджреНрд╡рд┐рддреАрдпрд╛",
        "pakshya": "рдЕрд╕реЛрдЬ рдХреГрд╖реНрдг рдкрдХреНрд╖ ЁЯМЦ",
        "nakshatra": "рдкреВрд░реНрд╡рднрд╛рджреНрд░рдкрджрд╛ upto 8:20:24, рдЙрдкрд░рд╛рдиреНрдд: рдЙрддреНрддрд░рднрд╛рджреНрд░рдкрджрд╛",
        "yoga": "рд╢реВрд▓ upto 12:19:36, рдЙрдкрд░рд╛рдиреНрдд: рдЧрдгреНрдб",
        "karan": "рдХреМрд▓рд╡ upto 13:36:6",
        "chandra_rashi": "рдореАрди тЩУ",
        "dinman": "31 рдШрдбреА 5 рдкрд▓рд╛ - 12hr 26min",
        "ritu": "рд╡рд░реНрд╖рд╛-Monsoon",
        "ayan": "рджрдХреНрд╖рд┐рдгрд╛рдпрди"
    }
}