[{"event": "धनु संक्रान्ति", "np": "१", "tithi": "द्वितीया", "en": "16", "model": {"np_date": "१ पुष २०७७, बुधवार ", "en_date": "December 16, 2020", "event": "धनु संक्रान्ति", "panchang": "पञ्चाङ्ग: वृद्धि बलव पूर्वाषाढ़ा"}}, {"event": "--", "np": "२", "tithi": "तृतिया", "en": "17", "model": {"np_date": "२ पुष २०७७, बिहिवार ", "en_date": "December 17, 2020", "event": "--", "panchang": "पञ्चाङ्ग: ध्रुव गरीजी उत्तराषाढ़ा"}}, {"event": "अन्तर्राष्ट्रिय आप्रवासी दिवस", "np": "३", "tithi": "चतुर्थी", "en": "18", "model": {"np_date": "३ पुष २०७७, शुक्रवार ", "en_date": "December 18, 2020", "event": "अन्तर्राष्ट्रिय आप्रवासी दिवस", "panchang": "पञ्चाङ्ग: ब्यघता भाद्र श्र\u200cावण"}}, {"event": "विवाह पञ्चमी", "np": "४", "tithi": "पञ्चमी", "en": "19", "model": {"np_date": "४ पुष २०७७, शनिवार  ", "en_date": "December 19, 2020", "event": "विवाह पञ्चमी", "panchang": "पञ्चाङ्ग: हर्षन बलव श्रविष्ठा"}}, {"event": "--", "np": "५", "tithi": "षष्ठी", "en": "20", "model": {"np_date": "५ पुष २०७७, आइतवार ", "en_date": "December 20, 2020", "event": "--", "panchang": "पञ्चाङ्ग: वज्र तैतुला शतभिषा"}}, {"event": "--", "np": "६", "tithi": "सप्तमी", "en": "21", "model": {"np_date": "६ पुष २०७७, सोमवार ", "en_date": "December 21, 2020", "event": "--", "panchang": "पञ्चाङ्ग: सिद्धि वनाजी पूर्वभाद्रपदा"}}, {"event": "--", "np": "७", "tithi": "अष्टमी", "en": "22", "model": {"np_date": "७ पुष २०७७, मंगलवार ", "en_date": "December 22, 2020", "event": "--", "panchang": "पञ्चाङ्ग: व्यतिपता बभ उत्तरभाद्रपदा"}}, {"event": "--", "np": "८", "tithi": "नवमी", "en": "23", "model": {"np_date": "८ पुष २०७७, बुधवार ", "en_date": "December 23, 2020", "event": "--", "panchang": "पञ्चाङ्ग: वरियन बलव रेवती"}}, {"event": "--", "np": "९", "tithi": "दशमी", "en": "24", "model": {"np_date": "९ पुष २०७७, बिहिवार ", "en_date": "December 24, 2020", "event": "--", "panchang": "पञ्चाङ्ग: परिघ तैतुला अश्विनि"}}, {"event": "--", "np": "११", "tithi": "द्वादशी", "en": "26", "model": {"np_date": "११ पुष २०७७, शनिवार ", "en_date": "December 26, 2020", "event": "--", "panchang": "पञ्चाङ्ग: सिद्ध बभ भरणी"}}, {"event": "--", "np": "१२", "tithi": "त्रयोदशी", "en": "27", "model": {"np_date": "१२ पुष २०७७, आइतवार ", "en_date": "December 27, 2020", "event": "--", "panchang": "पञ्चाङ्ग: साध्य कोउलव कृत्तिका"}}, {"event": "--", "np": "१३", "tithi": "चतुर्दशी", "en": "28", "model": {"np_date": "१३ पुष २०७७, सोमवार ", "en_date": "December 28, 2020", "event": "--", "panchang": "पञ्चाङ्ग: सुभ तैतुला रोहिणी"}}, {"event": "--", "np": "१४", "tithi": "चतुर्दशी", "en": "29", "model": {"np_date": "१४ पुष २०७७, मंगलवार ", "en_date": "December 29, 2020", "event": "--", "panchang": "पञ्चाङ्ग: सुकला वनाजी म्रृगशीर्षा"}}, {"event": "--", "np": "१६", "tithi": "प्रतिपदा", "en": "31", "model": {"np_date": "१६ पुष २०७७, बिहिवार ", "en_date": "December 31, 2020", "event": "--", "panchang": "पञ्चाङ्ग: इन्द्र कोउलव पुनर्वसु"}}, {"event": "सन् २०२१ प्रारम्भ", "np": "१७", "tithi": "द्वितीया", "en": "1", "model": {"np_date": "१७ पुष २०७७, शुक्रवार ", "en_date": "January 01, 2021", "event": "सन् २०२१ प्रारम्भ", "panchang": "पञ्चाङ्ग: वैधृति गरीजी पुष्य"}}, {"event": "--", "np": "१८", "tithi": "तृतिया", "en": "2", "model": {"np_date": "१८ पुष २०७७, शनिवार ", "en_date": "January 02, 2021", "event": "--", "panchang": "पञ्चाङ्ग: विश्कम्भ भाद्र आश्लेषा"}}, {"event": "--", "np": "१९", "tithi": "चतुर्थी", "en": "3", "model": {"np_date": "१९ पुष २०७७, आइतवार ", "en_date": "January 03, 2021", "event": "--", "panchang": "पञ्चाङ्ग: प्रिती बलव मघा"}}, {"event": "--", "np": "२०", "tithi": "षष्ठी", "en": "4", "model": {"np_date": "२० पुष २०७७, सोमवार ", "en_date": "January 04, 2021", "event": "--", "panchang": "पञ्चाङ्ग: अयुश्मान तैतुला पूर्व फाल्गुनी"}}, {"event": "गुरु गोबिन्द सिंह जयन्ती", "np": "२१", "tithi": "सप्तमी", "en": "5", "model": {"np_date": "२१ पुष २०७७, मंगलवार ", "en_date": "January 05, 2021", "event": "गुरु गोबिन्द सिंह जयन्ती", "panchang": "पञ्चाङ्ग: सौभाग्य वनाजी उत्तर फाल्गुनी"}}, {"event": "--", "np": "२२", "tithi": "अष्टमी", "en": "6", "model": {"np_date": "२२ पुष २०७७, बुधवार ", "en_date": "January 06, 2021", "event": "--", "panchang": "पञ्चाङ्ग: अतिगंदा बलव हस्त"}}, {"event": "--", "np": "२३", "tithi": "नवमी", "en": "7", "model": {"np_date": "२३ पुष २०७७, बिहिवार ", "en_date": "January 07, 2021", "event": "--", "panchang": "पञ्चाङ्ग: सुकर्मन तैतुला चित्रा"}}, {"event": "नेपाल ज्योतिष परिषद स्थापना दिवस", "np": "२४", "tithi": "दशमी", "en": "8", "model": {"np_date": "२४ पुष २०७७, शुक्रवार ", "en_date": "January 08, 2021", "event": "नेपाल ज्योतिष परिषद स्थापना दिवस", "panchang": "पञ्चाङ्ग: धृति वनाजी स्वाति"}}, {"event": "सफला एकादशी", "np": "२५", "tithi": "एकादशी", "en": "9", "model": {"np_date": "२५ पुष २०७७, शनिवार ", "en_date": "January 09, 2021", "event": "सफला एकादशी", "panchang": "पञ्चाङ्ग: सूल बभ विशाखा"}}, {"event": "--", "np": "२६", "tithi": "द्वादशी", "en": "10", "model": {"np_date": "२६ पुष २०७७, आइतवार ", "en_date": "January 10, 2021", "event": "--", "panchang": "पञ्चाङ्ग: गन्द कोउलव अनुराधा"}}, {"event": "पृथ्वी जयन्ती ", "np": "२७", "tithi": "त्रयोदशी", "en": "11", "model": {"np_date": "२७ पुष २०७७, सोमवार ", "en_date": "January 11, 2021", "event": "पृथ्वी जयन्ती ", "panchang": "पञ्चाङ्ग: वृद्धि वनाजी ज्येष्ठा"}}, {"event": "--", "np": "२८", "tithi": "चतुर्दशी", "en": "12", "model": {"np_date": "२८ पुष २०७७, मंगलवार ", "en_date": "January 12, 2021", "event": "--", "panchang": "पञ्चाङ्ग: ध्रुव सकुनी मूल"}}, {"event": "पौषे औँशी (गोकर्ण, बराहक्षेत्र आदीमा तिर्थ श्राद्ध)", "np": "२९", "tithi": "औंसी", "en": "13", "model": {"np_date": "२९ पुष २०७७, बुधवार ", "en_date": "January 13, 2021", "event": "पौषे औँशी (गोकर्ण, बराहक्षेत्र आदीमा तिर्थ श्राद्ध)", "panchang": "पञ्चाङ्ग: हर्षन नगवाम पूर्वाषाढ़ा"}}]