{
    "nepali_date": {
        "formated": "реи рд╡реИрд╢рд╛рдЦ реирежренрем, рд╕реЛрдорд╡рд╛рд░",
        "day": "реи",
        "month": "рд╡реИрд╢рд╛рдЦ",
        "year": "реирежренрем",
        "day_name": "рд╕реЛрдорд╡рд╛рд░",
        "date": "2076-01-02"
    },
    "english_date": {
        "formated": "April 15, 2019",
        "day": "15",
        "month": "April",
        "year": "2019",
        "day_name": "Monday",
        "date": "2019-04-15"
    },
    "nepali_sambat": {
        "formated": "1139 рдЪреМрд▓рд╛рдереНрд╡ рджрд╢рдореА-10",
        "year": "1139",
        "month": "рдЪреМрд▓рд╛рдереНрд╡",
        "tithi": "рджрд╢рдореА-10"
    },
    "event": "--",
    "is_holiday": false,
    "panchang": {
        "surya": "5:41тШАя╕П, 18:29ЁЯМд",
        "chandra": "14:21тШ╜, 2:59тШ╛",
        "tithi": "рджрд╢рдореА upto 7:23:53, рдЙрдкрд░рд╛рдиреНрдд: рдПрдХрд╛рджрд╢реА upto 28:39:41",
        "pakshya": "рдЪреИрддреНрд░ рд╢реБрдХреНрд▓ рдкрдХреНрд╖ ЁЯМФ",
        "nakshatra": "рдЕрд╢реНрд▓реЗрд╖рд╛ upto 6:15:50, рдЙрдкрд░рд╛рдиреНрдд:рдордШрд╛ (рд╕рдорд╛рдкреНрддреА)",
        "yoga": "рдЧрдгреНрдб upto 25:54:19, рдЙрдкрд░рд╛рдиреНрдд: рд╡реГрджреНрдзрд┐",
        "karan": "рдЧрд░ upto 7:23:53",
        "chandra_rashi": "рдХрд░реНрдХрдЯ тЩЛ upto 6:15:50, рдЙрдкрд░рд╛рдиреНрдд: рд╕рд┐рдВрд╣ тЩМ",
        "dinman": "32 рдШрдбреА 0 рдкрд▓рд╛ - 12hr 48min",
        "ritu": "рд╡рд╕рдиреНрдд-Spring",
        "ayan": "рдЙрддреНрддрд░рд╛рдпрдг"
    }
}