{
    "nepali_date": {
        "formated": "реирей рд╡реИрд╢рд╛рдЦ реирежренрем, рд╕реЛрдорд╡рд╛рд░",
        "day": "реирей",
        "month": "рд╡реИрд╢рд╛рдЦ",
        "year": "реирежренрем",
        "day_name": "рд╕реЛрдорд╡рд╛рд░",
        "date": "2076-01-23"
    },
    "english_date": {
        "formated": "May 06, 2019",
        "day": "6",
        "month": "May",
        "year": "2019",
        "day_name": "Monday",
        "date": "2019-05-06"
    },
    "nepali_sambat": {
        "formated": "1139 рд╡рдЫрд▓рд╛рдереНрд╡ рджреНрд╡рд┐рддреАрдпрд╛-2",
        "year": "1139",
        "month": "рд╡рдЫрд▓рд╛рдереНрд╡",
        "tithi": "рджреНрд╡рд┐рддреАрдпрд╛-2"
    },
    "event": "--",
    "is_holiday": false,
    "panchang": {
        "surya": "5:22тШАя╕П, 18:41ЁЯМд",
        "chandra": "6:20тШ╜, 20:00тШ╛",
        "tithi": "рджреНрд╡рд┐рддреАрдпрд╛ upto 27:33:21, рдЙрдкрд░рд╛рдиреНрдд: рддреГрддреАрдпрд╛",
        "pakshya": "рдмреИрд╢рд╛рдЦ рд╢реБрдХреНрд▓ рдкрдХреНрд╖ ЁЯМТ",
        "nakshatra": "рдХреГрддреНрддрд┐рдХрд╛ upto 16:50:40, рдЙрдкрд░рд╛рдиреНрдд: рд░реЛрд╣рд┐рдгреА",
        "yoga": "рд╢реЛрднрди upto 25:29:1, рдЙрдкрд░рд╛рдиреНрдд: рдЕрддрд┐рдЧрдВрдб",
        "karan": "рдмрд╛рд▓рд╡ upto 15:54:34, рдЙрдкрд░рд╛рдиреНрдд: рдХреМрд▓рд╡ upto 27:33:21",
        "chandra_rashi": "рд╡реГрд╖ тЩЙ",
        "dinman": "33 рдШрдбреА 17 рдкрд▓рд╛ - 13hr 19min",
        "ritu": "рд╡рд╕рдиреНрдд-Spring",
        "ayan": "рдЙрддреНрддрд░рд╛рдпрдг"
    }
}