{
    "nepali_date": {
        "formated": "реирен рднрджреМ реирежренрем, рд╢реБрдХреНрд░рд╡рд╛рд░",
        "day": "реирен",
        "month": "рднрджреМ",
        "year": "реирежренрем",
        "day_name": "рд╢реБрдХреНрд░рд╡рд╛рд░",
        "date": "2076-05-27"
    },
    "english_date": {
        "formated": "September 13, 2019",
        "day": "13",
        "month": "September",
        "year": "2019",
        "day_name": "Friday",
        "date": "2019-09-13"
    },
    "nepali_sambat": {
        "formated": "1139 рдЮрд▓рд╛рдереНрд╡ рдЪрддреБрд░реНрджрд╢реА-14",
        "year": "1139",
        "month": "рдЮрд▓рд╛рдереНрд╡",
        "tithi": "рдЪрддреБрд░реНрджрд╢реА-14"
    },
    "event": "--",
    "is_holiday": false,
    "panchang": {
        "surya": "5:48тШАя╕П, 18:13ЁЯМд",
        "chandra": "18:04тШ╜, 4:50тШ╛",
        "tithi": "рдЪрддреБрд░реНрджрд╢реА upto 7:51:27, рдЙрдкрд░рд╛рдиреНрдд: рдкреВрд░реНрдгрд┐рдорд╛",
        "pakshya": "рднрд╛рджреНрд░ рд╢реБрдХреНрд▓ рдкрдХреНрд╖ ЁЯМХ",
        "nakshatra": "рд╢рддрднрд┐рд╖рд╛ upto 20:15:4, рдЙрдкрд░рд╛рдиреНрдд: рдкреВрд░реНрд╡рднрд╛рджреНрд░рдкрджрд╛",
        "yoga": "рдзреГрддрд┐ upto 20:47:14, рдЙрдкрд░рд╛рдиреНрдд: рд╢реВрд▓",
        "karan": "рд╡рдгрд┐рдЬ upto 7:51:27",
        "chandra_rashi": "рдХреБрдореНрдн тЩТ",
        "dinman": "31 рдШрдбреА 2 рдкрд▓рд╛ - 12hr 25min",
        "ritu": "рд╡рд░реНрд╖рд╛-Monsoon",
        "ayan": "рджрдХреНрд╖рд┐рдгрд╛рдпрди"
    }
}