{
    "nepali_date": {
        "formated": "реирео рдорд╛рдШ реирежреореж, рдЖрдЗрддрд╡рд╛рд░",
        "day": "реирео",
        "month": "рдорд╛рдШ",
        "year": "реирежреореж",
        "day_name": "рдЖрдЗрддрд╡рд╛рд░",
        "date": "2080-10-28"
    },
    "english_date": {
        "formated": "February 11, 2024",
        "day": "11",
        "month": "February",
        "year": "2024",
        "day_name": "Sunday",
        "date": "2024-02-11"
    },
    "nepali_sambat": {
        "formated": "1144 рд╕рд┐рд▓реНрд▓рд╛рдереНрд╡ рджреНрд╡рд┐рддреАрдпрд╛-2",
        "year": "1144",
        "month": "рд╕рд┐рд▓реНрд▓рд╛рдереНрд╡",
        "tithi": "рджреНрд╡рд┐рддреАрдпрд╛-2"
    },
    "event": "рд╡рд┐рдЬреНрдЮрд╛рдирдорд╛ рдорд╣рд┐рд▓рд╛ рдкрд╣реБрдБрдЪрдХреЛ рдЕрдиреНрддрд░реНрд░рд╛рд╖реНрдЯреНрд░рд┐рдп рджрд┐рд╡рд╕",
    "is_holiday": false,
    "panchang": {
        "surya": "6:45тШАя╕П, 17:53ЁЯМд",
        "chandra": "7:48тШ╜, 19:25тШ╛",
        "tithi": "рджреНрд╡рд┐рддреАрдпрд╛ upto 21:27:39, рдЙрдкрд░рд╛рдиреНрдд: рддреГрддреАрдпрд╛",
        "pakshya": "рдорд╛рдШ рд╢реБрдХреНрд▓ рдкрдХреНрд╖ ЁЯМТ",
        "nakshatra": "рд╢рддрднрд┐рд╖рд╛ upto 17:57:37, рдЙрдкрд░рд╛рдиреНрдд: рдкреВрд░реНрд╡рднрд╛рджреНрд░рдкрджрд╛",
        "yoga": "рдкрд░рд┐рдШ upto 10:55:52, рдЙрдкрд░рд╛рдиреНрдд: рд╢рд┐рд╡",
        "karan": "рдмрд╛рд▓рд╡ upto 11:15:4, рдЙрдкрд░рд╛рдиреНрдд: рдХреМрд▓рд╡ upto 21:27:39",
        "chandra_rashi": "рдХреБрдореНрдн тЩТ",
        "dinman": "27 рдШрдбреА 50 рдкрд▓рд╛ - 11hr 8min",
        "ritu": "рд╢рд┐рд╢рд┐рд░-Winter",
        "ayan": "рдЙрддреНрддрд░рд╛рдпрдг"
    }
}